pyodide_mkdocs_theme_sqlite/__init__.py
pyodide_mkdocs_theme_sqlite/plugin.py
pyodide_mkdocs_theme_sqlite/css/sqlite_ide.css
pyodide_mkdocs_theme_sqlite/js/sql-wasm.wasm
pyodide_mkdocs_theme_sqlite/js/sqlite_ide.js
pyodide_mkdocs_theme_sqlite/js/worker.sql-wasm.js
pyodide_mkdocs_theme_sqlite-1.0.1.dist-info/METADATA
pyodide_mkdocs_theme_sqlite-1.0.1.dist-info/WHEEL
pyodide_mkdocs_theme_sqlite-1.0.1.dist-info/entry_points.txt
pyodide_mkdocs_theme_sqlite-1.0.1.dist-info/top_level.txt
pyodide_mkdocs_theme_sqlite-1.0.1.dist-info/RECORD
